click_migrator/__init__.py
click_migrator/migrator.py
click_migrator-0.6.0.dist-info/LICENSE
click_migrator-0.6.0.dist-info/METADATA
click_migrator-0.6.0.dist-info/WHEEL
click_migrator-0.6.0.dist-info/top_level.txt
click_migrator-0.6.0.dist-info/RECORD
