Metadata-Version: 2.1
Name: click-migrator
Version: 0.6.0
Summary: Solution for executing ClickHouse database migration scripts
Author-email: Evgrafov Alexander <evgrafov.alexander92@yandex.ru>
License: MIT License
Project-URL: Repository, https://github.com/EvgrafovAlexander/clickhouse_migrator
Requires-Python: >=3.8
License-File: LICENSE
Requires-Dist: clickhouse-driver
